Lab_8/q1/d_latch/dl.v
module dl(C,D,Q,_Q);
    input C;
    input D;

    output reg Q;
    output reg _Q;

    always @(C,D)
        begin
            case (C)
                0: begin
                    Q<=Q;
                    _Q<=_Q;
                end
                default: case (D)
                    0: begin
                        Q<=0;
                        _Q<=1;
                    end
                    1: begin
                        Q<=1;
                        _Q<=0;
                    end
                endcase
            endcase
        end
endmodule

Lab_8/q1/d_latch/dl_tb.v
`timescale 1ns/1ns
`include "dl.v"

module dl_tb();
    reg C;
    reg D;
    integer i;
    integer j;

    wire Q;
    wire _Q;

    dl DL(C,D,Q,_Q);

    initial
    begin
        $dumpfile("dl_tb.vcd");
        $dumpvars();
    end

    initial
    begin
        C=1;
        D=1;
        #10;
        D=0;
        #10;

        C=0;
        for(i=0;i<2;i=i+1)
        begin
            D=i;
            #10;
        end

        for(j=0;j<4;j=j+1)
        begin
            {C,D} = j;
            #10;
        end
    end

    initial
    begin
        $display("Test Completed");
    end
endmodule

Lab_8/q1/d_latch/dl_tb.vcd
$date
	Mon Dec 12 19:31:51 2022
$end
$version
	Icarus Verilog
$end
$timescale
	1ns
$end
$scope module dl_tb $end
$var wire 1 ! _Q $end
$var wire 1 " Q $end
$var reg 1 # C $end
$var reg 1 $ D $end
$var integer 32 % i [31:0] $end
$var integer 32 & j [31:0] $end
$scope module DL $end
$var wire 1 # C $end
$var wire 1 $ D $end
$var reg 1 " Q $end
$var reg 1 ! _Q $end
$upscope $end
$upscope $end
$enddefinitions $end
$comment Show the parameter values. $end
$dumpall
$end
#0
$dumpvars
bx &
bx %
1$
1#
1"
0!
$end
#10
1!
0"
0$
#20
b0 %
0#
#30
1$
b1 %
#40
0$
b0 &
b10 %
#50
1$
b1 &
#60
1#
0$
b10 &
#70
0!
1"
1$
b11 &
#80
b100 &
