DSD_project/ALU.v
//ALU processor

//Below are logical instructions
`define AND 4'd0    //operand1 AND operand2
`define EOR 4'd1    //operand1 EXOR operand2
`define ORR 4'd2    //operand1 OR operand2
`define ORN 4'd3    //operand1 NOR operand2
`define BIC 4'd4    //operand1 AND NOT operand2 (bit clear) i.e AB'


//Below are arithmetic instructions
`define ADD 4'd5    //operand1 + operand2
`define ADC 4'd6    //operand1 + operand2 + carry
`define SUB 4'd7    //operand1 - operand2
`define SBC 4'd8    //operand1 - operand2 + carry - 1
`define RSB 4'd9    //operand2 - operand1             (reverse subtract)
`define RSC 4'd10   //operand2 - operand1 + carry - 1 (reverse subtract with carry)

//Below are comparision instructions
`define TEQ 4'd11    //operand1 EXOR operand2  (Test equivalence i.e output=0 for equivalent numbers)
`define CMP 4'd12   //operand1 - operand2    (compare) used to find > or < 
`define CMN 4'd13    //operand1 + operand2   (compare if one operand in negative), can be used to compare absolute values

//Below are data movement operations
`define MOV 4'd14   //MOV operand2
`define MVN 4'd15   //MOV NOT operand2

module ALU_processor(opcode, operand_1, operand_2, out, prev_ALU_flag_NZCV, ALU_flag_NZCV);

parameter N = 32; 

input[3:0] opcode;	//opcode of operation
input wire [N-1:0] operand_1; 
input wire [N-1:0] operand_2;
input wire[3:0] prev_ALU_flag_NZCV; //old values of NZCV


//N = Negative result from ALU flag.
//Z = Zero result from ALU flag.
//C = ALU operation Carried out
//V = ALU operation oVerflowed

output reg[N-1:0] out; 
output reg [3:0] ALU_flag_NZCV; 	//update NZCV values of flag register

reg cin;
reg cout;
reg[N-1:0] inverted;

always @(*) 
  begin
  ALU_flag_NZCV = prev_ALU_flag_NZCV;
  
  if (opcode == `AND)
      begin
			out = operand_1 & operand_2;
			
      end
	  
  else if (opcode == `EOR)  
      begin
			out = operand_1 ^ operand_2;
			
	  end
	  
  else if (opcode == `ORR)  
      begin
			out = operand_1 | operand_2;
			
	  end
	  
  else if (opcode == `ORN)  
      begin
			out = ~(operand_1 | operand_2);
			
	  end
	  
  else if (opcode == `BIC) 
      begin
			out = operand_1 & (~operand_2);		
	  end
	  
	//--------------------------------------------------
  else if (opcode == `ADD) 
      begin
			{cin, out[N-2:0]} = operand_1[N-2:0]+operand_2[N-2:0]; 
			{cout, out[N-1]} = cin + operand_1[N-1]+operand_2[N-1];
			ALU_flag_NZCV[1]  = cout;	//carry flag
			ALU_flag_NZCV[0] = cin^cout; //overflow flag	
	  end	
	  
   else if (opcode == `ADC)	  
      begin
			{cin, out[N-2:0]} = operand_1[N-2:0]+operand_2[N-2:0]+prev_ALU_flag_NZCV[1]; 
			{cout, out[N-1]} = cin + operand_1[N-1]+operand_2[N-1];
			ALU_flag_NZCV[1]  = cout;	//carry flag
			ALU_flag_NZCV[0] = cin^cout; //overflow flag
		end
	
	else if (opcode == `SUB)
      begin
			inverted = -operand_2;
			{cin, out[N-2:0]} = operand_1[N-2:0]+inverted[N-2:0]; 
			{cout, out[N-1]} = cin + operand_1[N-1]+inverted[N-1];
			ALU_flag_NZCV[1]  = cout;	//carry flag
			ALU_flag_NZCV[0] = cin^cout; //overflow flag
		end	
		
    else if (opcode == `SBC)
	  begin
			inverted = -operand_2;
			{cin, out[N-2:0]} = operand_1[N-2:0]+inverted[N-2:0]+prev_ALU_flag_NZCV[1]-1; 
			{cout, out[N-1]} = cin + operand_1[N-1]+inverted[N-1];
			ALU_flag_NZCV[1]  = cout;	//carry flag
			ALU_flag_NZCV[0] = cin^cout; //overflow flag	
		end
		
	else if (opcode == `RSB)
	  begin
			inverted = -operand_1;
			{cin, out[N-2:0]} = operand_2[N-2:0]+inverted[N-2:0]; 
			{cout, out[N-1]} = cin+ operand_2[N-1]+inverted[N-1];
			ALU_flag_NZCV[1]  = cout;	//carry flag
			ALU_flag_NZCV[0] = cin^cout; //overflow flag
	  end
	  
	else if (opcode == `RSC)
	  begin
			inverted = -operand_1;
			{cin, out[N-2:0]} = operand_2[N-2:0]+inverted[N-2:0]+prev_ALU_flag_NZCV[1]-1; 
			{cout, out[N-1]} = cin + operand_2[N-1]+inverted[N-1];
			ALU_flag_NZCV[1]  = cout;	//carry flag
			ALU_flag_NZCV[0] = cin^cout; //overflow flag
	  end
	//--------------------------------------------------------------------------------------------		
		
	else if (opcode == `TEQ) 
	  begin
			out = operand_1 ^ operand_2;
			
      end
	
	else if (opcode == `CMP)
	  begin
			inverted = -operand_2;
			{cin, out[N-2:0]} = operand_1[N-2:0]+inverted[N-2:0]; 
			{cout, out[N-1]} = cin + operand_1[N-1]+inverted[N-1];
			ALU_flag_NZCV[1]  = cout;	//carry flag
			ALU_flag_NZCV[0] = cin^cout; //overflow flag
	  end
	
	else if (opcode == `CMN)
	  begin
			{cin, out[N-2:0]} = operand_1[N-2:0]+operand_2[N-2:0]; 
			{cout, out[N-1]} = cin + operand_1[N-1]+operand_2[N-1];
			ALU_flag_NZCV[1]  = cout;	//carry flag
			ALU_flag_NZCV[0] = cin^cout; //overflow flag
	  end
	 
    else if (opcode == `MOV)
      begin
			out = operand_2;
			
	  end
	  
    else if (opcode == `MVN)
      begin
			out = ~operand_2;
			
	 end	
	 //end if
	 
	 if (out == 0)
	 begin
	       ALU_flag_NZCV[2] = 1;
     end
	 ALU_flag_NZCV[3] = out[N-1];
	 
  end
endmodule

DSD_project/ALU_tb.v
//ALU testbench
`timescale 1ns/1ns
`include "ALU.v"

module ALU_processor_tb();
parameter N = 32;

reg[3:0] opcode;
reg[N-1:0] op1, op2;
wire[N-1:0] out;
wire[3:0] ALU_flag_NZCV;
wire[3:0] old_ALU_flag_NZCV = 4'b0000;


//reg [N-1:0]temp;
ALU_processor alu1(opcode, op1, op2, out, old_ALU_flag_NZCV, ALU_flag_NZCV); 

initial begin
    $dumpfile("ALU.vcd");
    $dumpvars();
end

initial begin
	
	opcode = 4'd0;
	op1 = 32'b11001001110010011100100111001001;
	op2 = 32'b10100011101000111010001110100011;
	#100
	$display("%b & %b = %b , NZCV:%b", op1, op2, out, ALU_flag_NZCV);
	//Expected output=10000001100000011000000110000001
    
	opcode = 4'd1;
	op1 = 32'b11001001110010011100100111001001;
	op2 = 32'b10100011101000111010001110100011;#100 
	$display("%b ^ %b = %b , NZCV:%b", op1, op2, out, ALU_flag_NZCV);
	//Expected output=01101010011010100110101001101010

    opcode = 4'd2;
	op1 = 32'b11001001110010011100100111001001;
	op2 = 32'b10100011101000111010001110100011;	#100 
	$display("%b | %b = %b , NZCV : %b", op1, op2, out, ALU_flag_NZCV);
	//Expected output=11101011111010111110101111101011
	
    opcode = 4'd3;
	op1 = 32'b11001001110010011100100111001001;
	op2 = 32'b10100011101000111010001110100011;#100 
	$display("%b NOR %b = %b , NZCV : %b", op1, op2, out, ALU_flag_NZCV);
    //Expected output=00010100000101000001010000010100
	
	 
    opcode = 4'd4;
	op1 = 32'b11001001110010011100100111001001;
	op2 = 32'b10100011101000111010001110100011;#100
	$display("%b BIC %b = %b , NZCV : %b", op1, op2, out, ALU_flag_NZCV);
	//Expected output=01001000010010000100100001001000
	
	opcode = 4'd5;
	op1 = 32'd1234;
	op2 = 32'd1234;#100
	$display("%0d + %0d = %0d , NZCV : %b", op1, op2, out, ALU_flag_NZCV);
	//Expected output=2468
	
	opcode = 4'd6;
	op1 = 32'd1234;
	op2 = 32'd5678;#100
	$display("%0d +c %0d = %0d , NZCV : %b", op1, op2, out, ALU_flag_NZCV);
	//Expected output 6912
	
	opcode = 4'd7;
	op1 = 32'd1234;
	op2 = 32'd1234;#100
	$display("%0d - %0d = %0d , NZCV : %b", op1, op2, out, ALU_flag_NZCV);
	//Expected output=0
	
	opcode = 4'd8;
	op1 = 32'd1234;
	op2 = 32'd1233;#100
	$display("%0d -c %0d = %0d , NZCV : %b", op1, op2, out, ALU_flag_NZCV);
	//Expected output=1, but in sbc operation output will be=0
	
	opcode = 4'd9;
	op1 = 32'd1234;
	op2 = 32'd5678;#100
	$display("%0d - %0d = %0d , NZCV : %b", op2, op1, out, ALU_flag_NZCV);
    //Expected output=4444
	
	
	opcode = 4'd10;
	op1 = 32'd1234;
	op2 = 32'd5678;#100
	$display("%0d -c %0d = %0d , NZCV : %b", op2, op1, out, ALU_flag_NZCV);
	//Expected output=4443
	
	opcode = 4'd11;
	op1 = 32'd1234;
	op2 = 32'd5678;#100
	$display("%0d teq %0d = %0d , NZCV : %b", op1, op2, out, ALU_flag_NZCV);
	//Expected output= not 0(not same)
	
	opcode = 4'd12;
	op1 = 32'd9999;
	op2 = 32'd1111;#100
	$display("%0d cmp %0d = %0d , NZCV : %b", op1, op2, out, ALU_flag_NZCV);
	//Expected output=8888
	
	opcode = 4'd13;
	op1 = 32'd1234;
	op2 = 32'd5678;#100
	$display("%0d cmn %0d = %0d , NZCV : %b", op1, op2, out, ALU_flag_NZCV);
	//Expected output=6912
	
	opcode = 4'd14;
	op1 = 32'd1234;
	op2 = 32'd5678;#100
	$display("%0d mov  %0d = %0d , NZCV : %b", op1, op2, out, ALU_flag_NZCV);
	//Expected output=5678
    
	opcode = 4'd15;
	op1 = 32'd1234;
	op2 = 32'd9999;#100 
	$display("%0d mvn %0d = %0d , NZCV : %b", op1, op2, out, ALU_flag_NZCV);
	
#100 $finish;	
end

endmodule

DSD_project/ALU.vcd
$date
	Wed Jan 18 14:15:00 2023
$end
$version
	Icarus Verilog
$end
$timescale
	1ns
$end
$scope module ALU_processor_tb $end
$var wire 4 ! old_ALU_flag_NZCV [3:0] $end
$var wire 32 " out [31:0] $end
$var wire 4 # ALU_flag_NZCV [3:0] $end
$var parameter 32 $ N $end
$var reg 32 % op1 [31:0] $end
$var reg 32 & op2 [31:0] $end
$var reg 4 ' opcode [3:0] $end
$scope module alu1 $end
$var wire 4 ( opcode [3:0] $end
$var wire 32 ) operand_1 [31:0] $end
$var wire 32 * operand_2 [31:0] $end
$var wire 4 + prev_ALU_flag_NZCV [3:0] $end
$var parameter 32 , N $end
$var reg 4 - ALU_flag_NZCV [3:0] $end
$var reg 1 . cin $end
$var reg 1 / cout $end
$var reg 32 0 inverted [31:0] $end
$var reg 32 1 out [31:0] $end
$upscope $end
$upscope $end
$enddefinitions $end
$comment Show the parameter values. $end
$dumpall
b100000 ,
b100000 $
$end
#0
$dumpvars
b10000001100000011000000110000001 1
bx 0
x/
x.
b1000 -
b0 +
b10100011101000111010001110100011 *
b11001001110010011100100111001001 )
b0 (
b0 '
b10100011101000111010001110100011 &
b11001001110010011100100111001001 %
b1000 #
b10000001100000011000000110000001 "
b0 !
$end
#100
b1101010011010100110101001101010 "
b1101010011010100110101001101010 1
b0 #
b0 -
b1 '
b1 (
#200
b1000 #
b1000 -
b11101011111010111110101111101011 "
b11101011111010111110101111101011 1
b10 '
b10 (
#300
b10100000101000001010000010100 "
b10100000101000001010000010100 1
b0 #
b0 -
b11 '
b11 (
#400
b1001000010010000100100001001000 "
b1001000010010000100100001001000 1
b100 '
b100 (
#500
0/
0.
b100110100100 "
b100110100100 1
b10011010010 &
b10011010010 *
b10011010010 %
b10011010010 )
b101 '
b101 (
#600
b1101100000000 "
b1101100000000 1
b1011000101110 &
b1011000101110 *
b110 '
b110 (
#700
b110 #
b110 -
1/
1.
b0 "
b0 1
b11111111111111111111101100101110 0
b10011010010 &
b10011010010 *
b111 '
b111 (
#800
b11111111111111111111101100101111 0
b110 #
b110 -
b10011010001 &
b10011010001 *
b1000 '
b1000 (
#900
b1000101011100 "
b1000101011100 1
b11111111111111111111101100101110 0
b10 #
b10 -
b1011000101110 &
b1011000101110 *
b1001 '
b1001 (
#1000
b1000101011011 "
b1000101011011 1
b10 #
b10 -
b1010 '
b1010 (
#1100
b1001011111100 "
b1001011111100 1
b0 #
b0 -
b1011 '
b1011 (
#1200
b10 #
b10 -
b10001010111000 "
b10001010111000 1
b11111111111111111111101110101001 0
b10001010111 &
b10001010111 *
b10011100001111 %
b10011100001111 )
b1100 '
b1100 (
#1300
0/
0.
b1101100000000 "
b1101100000000 1
b0 #
b0 -
b1011000101110 &
b1011000101110 *
b10011010010 %
b10011010010 )
b1101 '
b1101 (
#1400
b1011000101110 "
b1011000101110 1
b1110 '
b1110 (
#1500
b1000 #
b1000 -
b11111111111111111101100011110000 "
b11111111111111111101100011110000 1
b10011100001111 &
b10011100001111 *
b1111 '
b1111 (
