Lab_9/pl/pl.v
module accumulator (i,acc,clk,clr,overflow_flag);
    input [3:0]i;
    output [3:0]acc;
    reg [4:0]accum;
    input clk,clr;
    output overflow_flag;
    reg overflow_flag,carry;

    always @(posedge clk or posedge clr) begin
        if (clr) begin
            accum <= 5'b00000;
            carry <= 4'b0000;
        end
        else begin
            accum <= accum+i;
            if (accum>15)
            begin
                accum[4]<=0;
                overflow_flag<=1;
            end
            else begin
                overflow_flag=0;
            
        end
    end
    end
    assign acc=accum[3:0];
endmodule

Lab_9/pl/pl_tb.v
`timescale 1ns/1ns
`include "pl.v"

module accumulator_tb;

    reg [3:0]i;
    wire [3:0]acc;
    reg clk,clr;
    wire overflow_flag;

accumulator dut(i,acc,clk,clr,overflow_flag);

initial begin
    $dumpfile("pl_tb.vcd");;
    $dumpvars();
end

initial begin
    clk=0;
    forever #5 clk=~clk;
end

initial begin
    clr=1;i=0;
    #10 clr = 0;
    #10 i=2;
    #10 i =3;
    #10 i=10;
    #10 i=1;
    #50 $finish;
end
endmodule

Lab_9/pl/pl_tb.vcd
$date
	Mon Dec 26 15:44:25 2022
$end
$version
	Icarus Verilog
$end
$timescale
	1ns
$end
$scope module accumulator_tb $end
$var wire 1 ! overflow_flag $end
$var wire 4 " acc [3:0] $end
$var reg 1 # clk $end
$var reg 1 $ clr $end
$var reg 4 % i [3:0] $end
$scope module dut $end
$var wire 1 # clk $end
$var wire 1 $ clr $end
$var wire 4 & i [3:0] $end
$var wire 4 ' acc [3:0] $end
$var reg 5 ( accum [4:0] $end
$var reg 1 ) carry $end
$var reg 1 ! overflow_flag $end
$upscope $end
$upscope $end
$enddefinitions $end
$comment Show the parameter values. $end
$dumpall
$end
#0
$dumpvars
0)
b0 (
b0 '
b0 &
b0 %
1$
0#
b0 "
x!
$end
#5
1#
#10
0#
0$
#15
0!
1#
#20
0#
b10 %
b10 &
#25
b10 "
b10 '
b10 (
1#
#30
0#
b11 %
b11 &
#35
b101 "
b101 '
b101 (
1#
#40
0#
b1010 %
b1010 &
#45
b1111 "
b1111 '
b1111 (
1#
#50
0#
b1 %
b1 &
#55
b0 "
b0 '
b10000 (
1#
#60
0#
#65
b1 "
b1 '
1!
b1 (
1#
#70
0#
#75
b10 "
b10 '
b10 (
0!
1#
#80
0#
#85
b11 "
b11 '
b11 (
1#
#90
0#
#95
b100 "
b100 '
b100 (
1#
