Lab_5/pl_q3/pl_q3.v
module convertor(P,Q,k);
input k;
input [15:0]P;
output [15:0]Q;
reg [15:0]Q;
always @(k,P)
begin
case(k)
 0:begin
Q[15]=P[15];
Q[14]=P[15]^P[14];
Q[13]=P[14]^P[13];
Q[12]=P[13]^P[12];
Q[11]=P[12]^P[11];
Q[10]=P[11]^P[10];
Q[9]=P[10]^P[9];
Q[8]=P[9]^P[8];
Q[7]=P[8]^P[7];
Q[6]=P[7]^P[6];
Q[5]=P[6]^P[5];
Q[4]=P[5]^P[4];
Q[3]=P[4]^P[3];
Q[2]=P[3]^P[2];
Q[1]=P[2]^P[1];
Q[0]=P[1]^P[0];
 end
 1:
 begin 
 Q[15]=P[15];
Q[14]=P[15]^P[14];
Q[13]=P[15]^P[14]^P[13];
Q[12]=P[15]^P[14]^P[13]^P[12];
Q[11]=P[15]^P[14]^P[13]^P[12]^P[11];
Q[10]=P[15]^P[14]^P[13]^P[12]^P[11]^P[10];
Q[9]=P[15]^P[14]^P[13]^P[12]^P[11]^P[10]^P[9];
Q[8]=P[15]^P[14]^P[13]^P[12]^P[11]^P[10]^P[9]^P[8];
Q[7]=P[15]^P[14]^P[13]^P[12]^P[11]^P[10]^P[9]^P[8]^P[7];
Q[6]=P[15]^P[14]^P[13]^P[12]^P[11]^P[10]^P[9]^P[8]^P[7]^P[6];
Q[5]=P[15]^P[14]^P[13]^P[12]^P[11]^P[10]^P[9]^P[8]^P[7]^P[6]^P[5];
Q[4]=P[15]^P[14]^P[13]^P[12]^P[11]^P[10]^P[9]^P[8]^P[7]^P[6]^P[5]^P[4];
Q[3]=P[15]^P[14]^P[13]^P[12]^P[11]^P[10]^P[9]^P[8]^P[7]^P[6]^P[5]^P[4]^P[3];
Q[2]=P[15]^P[14]^P[13]^P[12]^P[11]^P[10]^P[9]^P[8]^P[7]^P[6]^P[5]^P[4]^P[3]^P[2];
Q[1]=P[15]^P[14]^P[13]^P[12]^P[11]^P[10]^P[9]^P[8]^P[7]^P[6]^P[5]^P[4]^P[3]^P[2]^P[1];
Q[0]=P[15]^P[14]^P[13]^P[12]^P[11]^P[10]^P[9]^P[8]^P[7]^P[6]^P[5]^P[4]^Q[3]^P[2]^P[1]^P[0];

 end 
endcase
end
endmodule

Lab_5/pl_q3/pl_q3_tb.v
`timescale 1ns/1ns
`include "pl_q3.v"
module pl_q3_tb();
reg [15:0] P;
reg k;
wire [15:0] Q;
convertor  c1(P,Q,k);
initial begin
    $dumpfile("pl_q3_tb.vcd");
    $dumpvars();
end
initial begin
k=0;
P=16'b1111111111111111;
#10;

k=0;
P=128;
#10;

k=0;
P=9;
#10;

k=0;
P=3;
#10;

k=0;
P=16'b1010101010101010;
#10;

k=1;
P=16'b1111111111111111;
#10;

k=1;
P=128;
#10;

k=1;
P=9;
#10;

k=1;
P=3;
#10;

k=1;
P=16'b1010101010101010;
#10;
end
endmodule

Lab_5/pl_q3/pl_q3_tb.vcd
$date
	Thu Nov 17 20:03:14 2022
$end
$version
	Icarus Verilog
$end
$timescale
	1ns
$end
$scope module pl_q3_tb $end
$var wire 16 ! Q [15:0] $end
$var reg 16 " P [15:0] $end
$var reg 1 # k $end
$scope module c1 $end
$var wire 16 $ P [15:0] $end
$var wire 1 # k $end
$var reg 16 % Q [15:0] $end
$upscope $end
$upscope $end
$enddefinitions $end
$comment Show the parameter values. $end
$dumpall
$end
#0
$dumpvars
b1000000000000000 %
b1111111111111111 $
0#
b1111111111111111 "
b1000000000000000 !
$end
#10
b11000000 !
b11000000 %
b10000000 "
b10000000 $
#20
b1101 !
b1101 %
b1001 "
b1001 $
#30
b10 !
b10 %
b11 "
b11 $
#40
b1111111111111111 !
b1111111111111111 %
b1010101010101010 "
b1010101010101010 $
#50
b1010101010101010 !
b1010101010101010 %
b1111111111111111 "
b1111111111111111 $
1#
#60
b11111110 !
b11111110 %
b10000000 "
b10000000 $
#70
b1110 !
b1110 %
b1001 "
b1001 $
#80
b10 !
b10 %
b11 "
b11 $
#90
b1100110011001100 !
b1100110011001100 %
b1010101010101010 "
b1010101010101010 $
