Lab_8/q2/johnson_counter.v
module johnsonCounter(clk,clr,load,D,Q);
    input clk;
    input clr;
    input load;
    input [7:0] D;

    output reg [7:0] Q;

    always @(load)
        Q = load ? D : Q;

    always @ (posedge clk)
    begin
        if(~load)
        begin
            if(clr) Q=0;
            else
            begin
                Q[7]<=Q[6];
                Q[6]<=Q[5];
                Q[5]<=Q[4];
                Q[4]<=Q[3];
                Q[3]<=Q[2];
                Q[2]<=Q[1];
                Q[1]<=Q[0];
                Q[0]<=~Q[7];
            end
        end
    end
endmodule

Lab_8/q2/jc_tb.v
`timescale 1ns/1ns
`include "johnson_counter.v"

module johnsonCounter_tb();
    reg clk;
    reg clr;
    reg load;
    reg [7:0] D;

    wire [7:0] Q;

    johnsonCounter JC(clk,clr,load,D,Q);

    initial
    begin
        $dumpfile("jc_tb.vcd");
        $dumpvars();
    end

    always
        #10 clk = ~clk;

    initial
    begin
        clk = 0;
        
        load = 0;
        clr = 1;
        #40;
        clr = 0;
        #40;

        load = 1;
        D = 0;
        clr = 0;
        #40;

        load = 0;
    end

    initial
    begin
        $display("Test Completed!!");
        #420 $finish;
    end
endmodule

Lab_8/q2/jc_tb.vcd
$date
	Mon Dec 12 20:33:51 2022
$end
$version
	Icarus Verilog
$end
$timescale
	1ns
$end
$scope module johnsonCounter_tb $end
$var wire 8 ! Q [7:0] $end
$var reg 8 " D [7:0] $end
$var reg 1 # clk $end
$var reg 1 $ clr $end
$var reg 1 % load $end
$scope module JC $end
$var wire 8 & D [7:0] $end
$var wire 1 # clk $end
$var wire 1 $ clr $end
$var wire 1 % load $end
$var reg 8 ' Q [7:0] $end
$upscope $end
$upscope $end
$enddefinitions $end
$comment Show the parameter values. $end
$dumpall
$end
#0
$dumpvars
bx '
bx &
0%
1$
0#
bx "
bx !
$end
#10
b0 !
b0 '
1#
#20
0#
#30
1#
#40
0#
0$
#50
b1 !
b1 '
1#
#60
0#
#70
b11 !
b11 '
1#
#80
b0 !
b0 '
0#
b0 "
b0 &
1%
#90
1#
#100
0#
#110
1#
#120
0#
0%
#130
b1 !
b1 '
1#
#140
0#
#150
b11 !
b11 '
1#
#160
0#
#170
b111 !
b111 '
1#
#180
0#
#190
b1111 !
b1111 '
1#
#200
0#
#210
b11111 !
b11111 '
1#
#220
0#
#230
b111111 !
b111111 '
1#
#240
0#
#250
b1111111 !
b1111111 '
1#
#260
0#
#270
b11111111 !
b11111111 '
1#
#280
0#
#290
b11111110 !
b11111110 '
1#
#300
0#
#310
b11111100 !
b11111100 '
1#
#320
0#
#330
b11111000 !
b11111000 '
1#
#340
0#
#350
b11110000 !
b11110000 '
1#
#360
0#
#370
b11100000 !
b11100000 '
1#
#380
0#
#390
b11000000 !
b11000000 '
1#
#400
0#
#410
b10000000 !
b10000000 '
1#
