Lab_5/q1/Q1b.v
module decoder24 (E,A,Y);
input E;
input [1:0] A;
output [0:3] Y;
reg [0:3] Y;
always @(E,A)
begin 
  if(E==1'b0)
   Y=0;
 else 
    if(A==0)
        Y=8;
 else   if(A==1)
        Y=4;
 else   if(A==2)
        Y=2;
 else   if(A==3)
        Y=1;
 end
endmodule

Lab_5/q1/Q1b_tb.v
`timescale 1ns/1ns
`include "Q1b.v"

module Q1b();

reg E;
reg [1:0] A;
wire [0:3] Y;
integer i; 

decoder24 d1(E,A,Y);

initial 
begin 
    $dumpfile("Q1b_tb.vcd");
    $dumpvars();
end

initial
begin
  E=1;
  for(i=0;i<4;i=i+1)
   begin 
    A=i;
    #10;
   end

  E=0;
  for(i=0;i<4;i=i+1)
   begin 
    A=i;
    #10;
   end
end

initial
    begin
            $display("Test Complete!");
        end

endmodule

Lab_5/q1/Q1a_tb.vcd
$date
	Sat Nov 12 20:44:36 2022
$end
$version
	Icarus Verilog
$end
$timescale
	1ns
$end
$scope module Q1b $end
$var wire 4 ! Y [0:3] $end
$var reg 2 " A [1:0] $end
$var reg 1 # E $end
$var integer 32 $ i [31:0] $end
$scope module d1 $end
$var wire 2 % A [1:0] $end
$var wire 1 # E $end
$var reg 4 & Y [0:3] $end
$upscope $end
$upscope $end
$enddefinitions $end
$comment Show the parameter values. $end
$dumpall
$end
#0
$dumpvars
b1000 &
b0 %
b0 $
1#
b0 "
b1000 !
$end
#10
b100 !
b100 &
b1 "
b1 %
b1 $
#20
b10 !
b10 &
b10 "
b10 %
b10 $
#30
b1 !
b1 &
b11 "
b11 %
b11 $
#40
b0 !
b0 &
b0 "
b0 %
0#
b0 $
#50
b1 "
b1 %
b1 $
#60
b10 "
b10 %
b10 $
#70
b11 "
b11 %
b11 $
#80
b100 $
