Lab_10/q3/q3.v
module dispenser(input clk, input reset, input [1:0] in, output reg p, output reg c);
reg [4:0] state;
reg [4:0] next_state;
parameter A = 5'b00000; 
parameter B = 5'b00100;
parameter C = 5'b01000;
parameter D = 5'b01101; 
parameter E = 5'b10011;
always @(posedge clk or posedge reset) begin
if (reset) begin
state <= A;
end else begin
state <= next_state;
end
end

always @(*) begin
next_state <= A;
{p,c} <=2'b00;
case (state)
A: begin
if(in == 2'b00)
next_state <= A;
else if(in == 2'b01)
next_state <= B;
else if(in == 2'b10)
next_state <= C;
end
B: begin
if(in == 2'b00)
next_state <= B;
else if(in == 2'b01)
next_state <= C;
else if(in == 2'b10)
next_state <= D;
end
C: begin
if(in == 2'b00)
next_state <= C;
else if(in == 2'b01)
next_state <= D;
else if(in == 2'b10)
next_state <= E;
end
D: begin
if(in == 2'b00)
next_state <= A;
else if(in == 2'b01)
next_state <= C;
else if(in == 2'b10)
next_state <= B;
end
E: begin
if(in == 2'b00)
next_state <= A;
else if(in == 2'b01)
next_state <= B;
else if(in == 2'b10)
next_state <= C;
end
endcase
{p,c} <= state[1:0];
end
endmodule

Lab_10/q3/q3_tb.v
`timescale 1ns/1ns
`include "q3.v"

module dispenser_tb();
reg clk;
reg reset;
reg [1:0] in;
wire p;
wire c;

dispenser d(clk, reset, in, p, c);

always #5 clk = ~clk; 

initial begin
    $dumpfile("Dispenser.vcd");
    $dumpvars();
end
initial begin
clk = 0;
reset = 1;
in = 0;
#5 reset = 0;
end

initial begin
    in = 2;#10;
    in = 1;#10;
    in = 0;#10;
    in = 2;#10;
    in = 2;#10;
    in = 1;#10;
    in = 1;#10;
    in = 1;#10;
    in = 0;#10;
    in = 1;#10;
    in = 2;#10;
    in = 0;#10;
end

initial begin
    #150 $finish;
end

endmodule

Lab_10/q3/Dispenser.vcd
$date
	Sat Dec 31 23:23:02 2022
$end
$version
	Icarus Verilog
$end
$timescale
	1ns
$end
$scope module dispenser_tb $end
$var wire 1 ! p $end
$var wire 1 " c $end
$var reg 1 # clk $end
$var reg 2 $ in [1:0] $end
$var reg 1 % reset $end
$scope module d $end
$var wire 1 # clk $end
$var wire 2 & in [1:0] $end
$var wire 1 % reset $end
$var parameter 5 ' A $end
$var parameter 5 ( B $end
$var parameter 5 ) C $end
$var parameter 5 * D $end
$var parameter 5 + E $end
$var reg 1 " c $end
$var reg 5 , next_state [4:0] $end
$var reg 1 ! p $end
$var reg 5 - state [4:0] $end
$upscope $end
$upscope $end
$enddefinitions $end
$comment Show the parameter values. $end
$dumpall
b10011 +
b1101 *
b1000 )
b100 (
b0 '
$end
#0
$dumpvars
b0 -
b1000 ,
b10 &
1%
b10 $
0#
0"
0!
$end
#5
b10011 ,
b1000 -
0%
1#
#10
b1101 ,
0#
b1 $
b1 &
#15
1"
b1000 ,
b1101 -
1#
#20
1"
b0 ,
0#
b0 $
b0 &
#25
0"
b0 -
1#
#30
b1000 ,
0#
b10 $
b10 &
#35
b10011 ,
b1000 -
1#
#40
0#
#45
1!
1"
b1000 ,
b10011 -
1#
#50
1!
1"
b100 ,
0#
b1 $
b1 &
#55
0!
0"
b1000 ,
b100 -
1#
#60
0#
#65
b1101 ,
b1000 -
1#
#70
0#
#75
1"
b1000 ,
b1101 -
1#
#80
1"
b0 ,
0#
b0 $
b0 &
#85
0"
b0 -
1#
#90
b100 ,
0#
b1 $
b1 &
#95
b1000 ,
b100 -
1#
#100
b1101 ,
0#
b10 $
b10 &
#105
1"
b100 ,
b1101 -
1#
#110
1"
b0 ,
0#
b0 $
b0 &
#115
0"
b0 -
1#
