Lab_10/q2/q2_a.v
module seq_detector(input clk, input reset, input in, output reg match);
reg [2:0] state;
reg [2:0] next_state;
parameter S0 = 3'b000; 
parameter S1 = 3'b001;
parameter S2 = 3'b010;
parameter S3 = 3'b011; 
parameter S4 = 3'b100;
parameter S5 = 3'b101;
parameter S6 = 3'b110;

always @(posedge clk or posedge reset) begin
if (reset) begin
state <= S0;
end else begin
state <= next_state;
end
end

always @(*) begin
match <= 1'b0;
next_state <= S0;
case (state)
S0: begin
if (in == 1'b0)
next_state <= S2;
else next_state <=S1;
end
S1: begin
if (in == 1'b1) begin
next_state <= S1;
end else if (in == 1'b0) begin
next_state <= S4;
end
end
S2: begin
if (in == 1'b1) begin
next_state <= S3;
end else if (in == 1'b0) begin
next_state <= S2;
end
end
S3: begin
if (in == 1'b0) begin
next_state <= S4;
end else if (in == 1'b1) begin
next_state <= S5;
end
end
S4: begin
if (in == 1'b0) begin
next_state <= S6;
end else if (in == 1'b1) begin
next_state <= S3;
end
end
S5: begin
if (in == 1'b0) begin
next_state <= S0;
match<=1'b1;
end else if (in == 1'b1) begin
next_state <= S1;
end
end
S6: begin
if (in == 1'b0) begin
next_state <= S2;
end else if (in == 1'b1) begin
next_state <= S0;
match<= 1'b1;
end
end
endcase
end
endmodule

Lab_10/q2/q2_a_tb.v
`timescale 1ns/1ns
`include "q2_a.v"

module seq_detector_tb();
reg clk;
reg reset;
reg in;
wire match;

seq_detector dut(clk, reset, in, match);

always #5 clk = ~clk; 

initial begin
    $dumpfile("Mealy.vcd");
    $dumpvars();
end
initial begin
clk = 0;
reset = 1;
in = 0;
#5 reset = 0;
end

initial begin
    in = 1;#10;
    in = 0;#10;
    in = 1;#10;
    in = 0;#10;
    in = 0;#10;
    in = 1;#10;
    in = 0;#10;
    in = 1;#10;
    in = 1;#10;
    in = 0;#10;
    in = 1;#10;
    in = 1;#10;
    in = 0;#10;
    in = 0;#10;
    in = 1;#10;
    in = 1;#10;
    in = 0;#10;
    in = 1;#10;
end

initial begin
    #200 $finish;
end

endmodule

Lab_10/q2/Mealy.vcd
$date
	Sat Dec 31 22:54:13 2022
$end
$version
	Icarus Verilog
$end
$timescale
	1ns
$end
$scope module seq_detector_tb $end
$var wire 1 ! match $end
$var reg 1 " clk $end
$var reg 1 # in $end
$var reg 1 $ reset $end
$scope module dut $end
$var wire 1 " clk $end
$var wire 1 # in $end
$var wire 1 $ reset $end
$var parameter 3 % S0 $end
$var parameter 3 & S1 $end
$var parameter 3 ' S2 $end
$var parameter 3 ( S3 $end
$var parameter 3 ) S4 $end
$var parameter 3 * S5 $end
$var parameter 3 + S6 $end
$var reg 1 ! match $end
$var reg 3 , next_state [2:0] $end
$var reg 3 - state [2:0] $end
$upscope $end
$upscope $end
$enddefinitions $end
$comment Show the parameter values. $end
$dumpall
b110 +
b101 *
b100 )
b11 (
b10 '
b1 &
b0 %
$end
#0
$dumpvars
b0 -
b1 ,
1$
1#
0"
0!
$end
#5
b1 ,
b1 -
0$
1"
#10
b100 ,
0"
0#
#15
b110 ,
b100 -
1"
#20
b11 ,
0"
1#
#25
b101 ,
b11 -
1"
#30
b100 ,
0"
0#
#35
b110 ,
b100 -
1"
#40
0"
#45
b10 ,
b110 -
1"
#50
1!
b0 ,
0"
1#
#55
b1 ,
0!
b0 -
1"
#60
b10 ,
0"
0#
#65
b10 ,
b10 -
1"
#70
b11 ,
0"
1#
#75
b101 ,
b11 -
1"
#80
0"
#85
b1 ,
b101 -
1"
#90
1!
b0 ,
0"
0#
#95
b10 ,
0!
b0 -
1"
#100
b1 ,
0"
1#
#105
b1 ,
b1 -
1"
#110
0"
#115
1"
#120
b100 ,
0"
0#
#125
b110 ,
b100 -
1"
#130
0"
#135
b10 ,
b110 -
1"
#140
1!
b0 ,
0"
1#
#145
b1 ,
0!
b0 -
1"
#150
0"
#155
b1 ,
b1 -
1"
#160
b100 ,
0"
0#
#165
b110 ,
b100 -
1"
#170
b11 ,
0"
1#
#175
b101 ,
b11 -
1"
#180
0"
#185
b1 ,
b101 -
1"
#190
0"
#195
b1 ,
b1 -
1"
