Lab_5/q3/Q3b.v
module mux81b(S,i7,i6,i5,i4,i3,i2,i1,i0,Y);
 input [2:0] S;
 input [3:0] i7;
 input [3:0] i6;
 input [3:0] i5;
 input [3:0] i4;
 input [3:0] i3;
 input [3:0] i2;
 input [3:0] i1;
 input [3:0] i0;
 output [3:0] Y;
 reg [3:0] Y;
always @(S,i7,i6,i5,i4,i3,i2,i1,i0) 
begin
    if(S==0)
      Y=i0;
 else if(S==1)
      Y=i1;
 else if(S==2)
      Y=i2;
 else if(S==3)
      Y=i3;
 else if(S==4)
      Y=i4;
 else if(S==5)
      Y=i5;
 else if(S==6)
      Y=i6;
 else if(S==7)
      Y=i7;
end
endmodule

Lab_5/q3/Q3b_tb.v
`timescale 1ns/1ns
`include "Q3b.v"

module Q3b();
 reg [2:0] S;
 reg [3:0] i7;
 reg [3:0] i6;
 reg [3:0] i5;
 reg [3:0] i4;
 reg [3:0] i3;
 reg [3:0] i2;
 reg [3:0] i1;
 reg [3:0] i0;
 wire [3:0] Y;
 integer j;
mux81b m1 (S,i7,i6,i5,i4,i3,i2,i1,i0,Y);

initial begin
    $dumpfile("Q3b_tb.vcd");
    $dumpvars();
end

initial begin
   i7=7;
   i6=6;
   i5=5;
   i4=4;
   i3=3;
   i2=2;
   i1=1;
   i0=0;
   for(j=0;j<8;j=j+1)
    begin 
        S=j;
        #10;
    end
end

initial begin 
    $display("Test complete!");
end

endmodule

Lab_5/q3/Q3b_tb.vcd
$date
	Sat Nov 12 22:46:00 2022
$end
$version
	Icarus Verilog
$end
$timescale
	1ns
$end
$scope module Q3b $end
$var wire 4 ! Y [3:0] $end
$var reg 3 " S [2:0] $end
$var reg 4 # i0 [3:0] $end
$var reg 4 $ i1 [3:0] $end
$var reg 4 % i2 [3:0] $end
$var reg 4 & i3 [3:0] $end
$var reg 4 ' i4 [3:0] $end
$var reg 4 ( i5 [3:0] $end
$var reg 4 ) i6 [3:0] $end
$var reg 4 * i7 [3:0] $end
$var integer 32 + j [31:0] $end
$scope module m1 $end
$var wire 3 , S [2:0] $end
$var wire 4 - i0 [3:0] $end
$var wire 4 . i1 [3:0] $end
$var wire 4 / i2 [3:0] $end
$var wire 4 0 i3 [3:0] $end
$var wire 4 1 i4 [3:0] $end
$var wire 4 2 i5 [3:0] $end
$var wire 4 3 i6 [3:0] $end
$var wire 4 4 i7 [3:0] $end
$var reg 4 5 Y [3:0] $end
$upscope $end
$upscope $end
$enddefinitions $end
$comment Show the parameter values. $end
$dumpall
$end
#0
$dumpvars
b0 5
b111 4
b110 3
b101 2
b100 1
b11 0
b10 /
b1 .
b0 -
b0 ,
b0 +
b111 *
b110 )
b101 (
b100 '
b11 &
b10 %
b1 $
b0 #
b0 "
b0 !
$end
#10
b1 !
b1 5
b1 "
b1 ,
b1 +
#20
b10 !
b10 5
b10 "
b10 ,
b10 +
#30
b11 !
b11 5
b11 "
b11 ,
b11 +
#40
b100 !
b100 5
b100 "
b100 ,
b100 +
#50
b101 !
b101 5
b101 "
b101 ,
b101 +
#60
b110 !
b110 5
b110 "
b110 ,
b110 +
#70
b111 !
b111 5
b111 "
b111 ,
b111 +
#80
b1000 +
