Lab_8/q1/jkff/jkff.v
module jkff(clk,J,K,pr,clr,Q,_Q);
    input clk;
    input J;
    input K;
    input pr;
    input clr;

    output reg Q;
    output reg _Q;

    always @(posedge clk)
    begin
        if(pr)
        begin
            Q<=1;
            _Q<=0;
        end
        else if(clr)
        begin
            Q<=0;
            _Q<=1;
        end
        else
        begin
            case({J,K})
                2'b00: begin
                    Q<=Q;
                    _Q<=_Q;
                end
                2'b01: begin
                    Q<=0;
                    _Q<=1;
                end
                2'b10: begin
                    Q<=1;
                    _Q<=0;
                end
                2'b11: begin
                    Q<=~Q;
                    _Q<=~_Q;
                end
            endcase
        end
    end
endmodule

Lab_8/q1/jkff/jkff_tb.v
`timescale 1ns/1ns
`include "jkff.v"

module jkff_tb();
    reg clk;
    reg J;
    reg K;
    reg pr;
    reg clr;

    wire Q;
    wire _Q;

    jkff JF(clk,J,K,pr,clr,Q,_Q);

    initial
    begin
        $dumpfile("jkff_tb.vcd");
        $dumpvars();
    end

    always
        #5 clk = ~clk;

    initial
    begin
        clk=0;

        //Q=0
        J=0;
        K=1;
        pr=0;
        clr=0;
        #10;

        //Memory
        J=0;
        K=0;
        pr=0;
        clr=0;
        #10;

        //Testing preset
        J=0;
        K=1;
        pr=1;
        clr=0;
        #10;

        //Testing Clear
        J=0;
        K=1;
        pr=0;
        clr=1;
        #10;

        //Q=1
        J=1;
        K=0;
        pr=0;
        clr=0;
        #10;

        //Toggle
        J=1;
        K=1;
        pr=0;
        clr=0;
        #30;
    end

    initial
    begin
        $display("Test Completed!!");
        #70 $finish;
    end
endmodule

Lab_8/q1/jkff/jkff_tb.vcd
$date
	Mon Dec 12 19:50:18 2022
$end
$version
	Icarus Verilog
$end
$timescale
	1ns
$end
$scope module jkff_tb $end
$var wire 1 ! _Q $end
$var wire 1 " Q $end
$var reg 1 # J $end
$var reg 1 $ K $end
$var reg 1 % clk $end
$var reg 1 & clr $end
$var reg 1 ' pr $end
$scope module JF $end
$var wire 1 # J $end
$var wire 1 $ K $end
$var wire 1 % clk $end
$var wire 1 & clr $end
$var wire 1 ' pr $end
$var reg 1 " Q $end
$var reg 1 ! _Q $end
$upscope $end
$upscope $end
$enddefinitions $end
$comment Show the parameter values. $end
$dumpall
$end
#0
$dumpvars
0'
0&
0%
1$
0#
x"
x!
$end
#5
1!
0"
1%
#10
0%
0$
#15
1%
#20
0%
1'
1$
#25
0!
1"
1%
#30
0%
1&
0'
#35
1!
0"
1%
#40
0%
0&
0$
1#
#45
0!
1"
1%
#50
0%
1$
#55
1!
0"
1%
#60
0%
#65
0!
1"
1%
