Lab_5/pl_q2/Q4.v
module mux4to1 (Y,S1,S0,I0,I1,I2,I3);

    input S1;
    input S0;
    input I3;
    input I2;
    input I1;
    input I0;

    output Y;

    assign Y = S1 ? (S0 ? I3 : I2) : (S0 ? I1 : I0);

endmodule

Lab_5/pl_q2/pl_q2.v
`include "Q4.v"
module seg7display (p,q,r,s,a,b,c,d,e,f,g); 
input p;
input q;
input r;
input s;
output a;
output b;
output c;
output d;
output e;
output f;
output g;
mux4to1 m1(a,p,q,(r|~s),(r|s),1'b1,1'bx);
mux4to1 m2(b,p,q,1'b1,((r&s)|(~r&~s)),1'b1,1'bx);
mux4to1 m3(c,p,q,(~r|s),1'b1,1'b1,1'bx);
mux4to1 m4(d,p,q,(r|~s),((~r&s)|(r&~s)),1'b1,1'bx);
mux4to1 m5(e,p,q,(~s),(r&~s),(~s),1'bx);
mux4to1 m6(f,p,q,(~(r|s)),(~(r&s)),1'b1,1'bx);
mux4to1 m7(g,p,q,r,(~(r&s)),1'b1,1'bx);
    
endmodule

Lab_5/pl_q2/pl_q2_tb.v
`timescale 1ns/1ns
`include "pl_q2.v"
module pl_q2_tb();
reg [3:0] B;
wire a;
wire b;
wire c;
wire d;
wire e;
wire f;
wire g;
integer i;
seg7display s1(B[3],B[2],B[1],B[0],a,b,c,d,e,f,g);
initial begin
    $dumpfile("pl_q2_tb.vcd");
    $dumpvars();
end
initial begin
    for(i=0;i<10;i=i+1)
    begin
     B=i;
     #10;
    end
end

endmodule

Lab_5/pl_q2/pl_q2_tb.vcd
$date
	Wed Nov 16 19:16:23 2022
$end
$version
	Icarus Verilog
$end
$timescale
	1ns
$end
$scope module pl_q2_tb $end
$var wire 1 ! g $end
$var wire 1 " f $end
$var wire 1 # e $end
$var wire 1 $ d $end
$var wire 1 % c $end
$var wire 1 & b $end
$var wire 1 ' a $end
$var reg 4 ( B [3:0] $end
$var integer 32 ) i [31:0] $end
$scope module s1 $end
$var wire 1 * p $end
$var wire 1 + q $end
$var wire 1 , r $end
$var wire 1 - s $end
$var wire 1 ! g $end
$var wire 1 " f $end
$var wire 1 # e $end
$var wire 1 $ d $end
$var wire 1 % c $end
$var wire 1 & b $end
$var wire 1 ' a $end
$scope module m1 $end
$var wire 1 . I0 $end
$var wire 1 / I1 $end
$var wire 1 0 I2 $end
$var wire 1 1 I3 $end
$var wire 1 + S0 $end
$var wire 1 * S1 $end
$var wire 1 ' Y $end
$upscope $end
$scope module m2 $end
$var wire 1 2 I0 $end
$var wire 1 3 I1 $end
$var wire 1 4 I2 $end
$var wire 1 5 I3 $end
$var wire 1 + S0 $end
$var wire 1 * S1 $end
$var wire 1 & Y $end
$upscope $end
$scope module m3 $end
$var wire 1 6 I0 $end
$var wire 1 7 I1 $end
$var wire 1 8 I2 $end
$var wire 1 9 I3 $end
$var wire 1 + S0 $end
$var wire 1 * S1 $end
$var wire 1 % Y $end
$upscope $end
$scope module m4 $end
$var wire 1 : I0 $end
$var wire 1 ; I1 $end
$var wire 1 < I2 $end
$var wire 1 = I3 $end
$var wire 1 + S0 $end
$var wire 1 * S1 $end
$var wire 1 $ Y $end
$upscope $end
$scope module m5 $end
$var wire 1 > I0 $end
$var wire 1 ? I1 $end
$var wire 1 @ I2 $end
$var wire 1 A I3 $end
$var wire 1 + S0 $end
$var wire 1 * S1 $end
$var wire 1 # Y $end
$upscope $end
$scope module m6 $end
$var wire 1 B I0 $end
$var wire 1 C I1 $end
$var wire 1 D I2 $end
$var wire 1 E I3 $end
$var wire 1 + S0 $end
$var wire 1 * S1 $end
$var wire 1 " Y $end
$upscope $end
$scope module m7 $end
$var wire 1 , I0 $end
$var wire 1 F I1 $end
$var wire 1 G I2 $end
$var wire 1 H I3 $end
$var wire 1 + S0 $end
$var wire 1 * S1 $end
$var wire 1 ! Y $end
$upscope $end
$upscope $end
$upscope $end
$enddefinitions $end
$comment Show the parameter values. $end
$dumpall
$end
#0
$dumpvars
xH
1G
1F
xE
1D
1C
1B
xA
1@
0?
1>
x=
1<
0;
1:
x9
18
17
16
x5
14
13
12
x1
10
0/
1.
0-
0,
0+
0*
b0 )
b0 (
1'
1&
1%
1$
1#
1"
0!
$end
#10
0'
0$
0"
03
0#
0.
0:
1;
0B
1/
0>
0@
1-
b1 (
b1 )
#20
0%
1'
1$
1#
06
1!
1.
1:
1?
1>
1@
1,
0-
b10 (
b10 )
#30
1%
0;
0#
13
0?
0C
0F
16
0>
0@
1-
b11 (
b11 )
#40
1"
0'
0$
1!
1B
1C
1F
0/
16
1>
1@
1+
0,
0-
b100 (
b100 )
#50
0&
1$
1'
03
0.
0:
1;
0B
1/
0>
0@
1-
b101 (
b101 )
#60
1#
06
1.
1:
1?
1>
1@
1,
0-
b110 (
b110 )
#70
0$
1&
0#
0"
0!
0;
13
0?
0C
0F
16
0>
0@
1-
b111 (
b111 )
#80
1B
1C
1F
1$
1#
1"
1!
0/
16
1>
1@
1*
0+
0,
0-
b1000 (
b1000 )
#90
03
0#
0.
0:
1;
0B
1/
0>
0@
1-
b1001 (
b1001 )
#100
b1010 )
