Lab_5/q4/Q4.v
module adder_subtractor(a,b,c_bin,s_d,c_bout,k);
 input [3:0] a;
 input [3:0] b;
 input c_bin;
 input k;
 output c_bout;
 output [3:0] s_d;
 reg [3:0] s_d;
 reg c_bout;
 reg [1:0] temp;
 reg u;
 integer i;
always @(a,b,c_bin)
 begin
    case(k)
    0:begin
      u=c_bin;
      for(i=0;i<4;i=i+1)
       begin
      //  temp=a[i]+b[i]+u;
      //  s_d[i]=temp[0];
      //  u=temp[1];
      s_d[i]=a[i]^b[i]^u;
      u= a[i]&b[i]|b[i]&u|u&a[i];
       end
       c_bout=u;
      end
    1:begin
      u=c_bin;
      for(i=0;i<4;i++)
       begin
       temp=a[i]-b[i]-u;
       s_d[i]=temp[0];
       u=temp[1];
       end
      c_bout=u;
      end
    endcase
 end
endmodule

Lab_5/q4/Q4_tb.v
`timescale 1ns / 1ns
`include "Q4.v"

module Q4_tb;

    reg [3:0] A;
    reg [3:0] B;
    reg c_bi;
    reg k;

    wire [3:0] s_d;
    wire c_bo;

    adder_subtractor A1 (A,B,c_bi,s_d,c_bo,k);

    initial
        begin
            $dumpfile("Q4_tb.vcd");
            $dumpvars();
        end

    initial
        begin
           k=0;
           begin A=0;
            B=0;
            c_bi=0;
            #10;

            A=15;
            B=15;
            c_bi=1;
            #10;

            A=0;
            B=15;
            c_bi=0;
            #10;

            A=15;
            B=0;
            c_bi=0;
            #10;

            A=10;
            B=10;
            c_bi=1;
            #10;

            A=10;
            B=5;
            c_bi=1;
            #10;
           end 
           k=1;
             begin A=0;
            B=0;
            c_bi=0;
            #10;

            A=15;
            B=15;
            c_bi=1;
            #10;

            A=0;
            B=15;
            c_bi=0;
            #10;

            A=15;
            B=0;
            c_bi=0;
            #10;

            A=10;
            B=10;
            c_bi=1;
            #10;

            A=10;
            B=5;
            c_bi=1;
            #10;
           end    
        end

    initial
        begin
            $display("Test Complete!");
        end

endmodule

Lab_5/q4/Q4_tb.vcd
$date
	Mon Jan 09 21:10:31 2023
$end
$version
	Icarus Verilog
$end
$timescale
	1ns
$end
$scope module Q4_tb $end
$var wire 4 ! s_d [3:0] $end
$var wire 1 " c_bo $end
$var reg 4 # A [3:0] $end
$var reg 4 $ B [3:0] $end
$var reg 1 % c_bi $end
$var reg 1 & k $end
$scope module A1 $end
$var wire 4 ' a [3:0] $end
$var wire 4 ( b [3:0] $end
$var wire 1 % c_bin $end
$var wire 1 & k $end
$var reg 1 " c_bout $end
$var reg 4 ) s_d [3:0] $end
$var reg 2 * temp [1:0] $end
$var reg 1 + u $end
$var integer 32 , i [31:0] $end
$upscope $end
$upscope $end
$enddefinitions $end
$comment Show the parameter values. $end
$dumpall
$end
#0
$dumpvars
b100 ,
0+
bx *
b0 )
b0 (
b0 '
0&
0%
b0 $
b0 #
0"
b0 !
$end
#10
1"
b1111 !
b1111 )
b100 ,
1+
1%
b1111 $
b1111 (
b1111 #
b1111 '
#20
0"
b100 ,
0+
0%
b0 #
b0 '
#30
b100 ,
b0 $
b0 (
b1111 #
b1111 '
#40
1"
b101 !
b101 )
b100 ,
1+
1%
b1010 $
b1010 (
b1010 #
b1010 '
#50
b0 !
b0 )
b100 ,
b101 $
b101 (
#60
0"
b0 *
b100 ,
0+
0%
b0 $
b0 (
b0 #
b0 '
1&
#70
1"
b1111 !
b1111 )
b11 *
b100 ,
1+
1%
b1111 $
b1111 (
b1111 #
b1111 '
#80
b1 !
b1 )
b10 *
b100 ,
1+
0%
b0 #
b0 '
#90
0"
b1111 !
b1111 )
b1 *
b100 ,
0+
b0 $
b0 (
b1111 #
b1111 '
#100
1"
b11 *
b100 ,
1+
1%
b1010 $
b1010 (
b1010 #
b1010 '
#110
0"
0+
b100 !
b100 )
b0 *
b100 ,
b101 $
b101 (
