Lab_8/q4/shifter.v
module shiftReg4bit(clk,clr,S,PL,Q);
    input clk;
    input clr;
    input [1:0] S;
    input [3:0] PL;

    output reg [3:0] Q;

    always @(posedge clk)
    begin
        if(clr) Q=0;
        else
        begin
            case(S)
                2'b00: Q <= Q;
                2'b01: Q <= {PL[0],PL[3],PL[2],PL[1]};
                2'b10: Q <= {PL[2],PL[1],PL[0],PL[3]};
                2'b11: Q <= PL;
            endcase
        end
    end
endmodule

Lab_8/q4/shifter_tb.v
`timescale 1ns/1ns
`include "shifter.v"

module shiftReg4bit_tb;
    reg clk;
    reg clr;
    reg [1:0] S;
    reg [3:0] PL;

    wire [3:0] Q;

    shiftReg4bit SR(clk,clr,S,PL,Q);

    initial
    begin
        $dumpfile("shifter_tb.vcd");
        $dumpvars();
    end

    always
        #5 clk = ~clk;

    initial
    begin
        clk=0;

        PL=4'b1001;
        S=2'b01;
        clr=0;
        #10;

        PL=4'b1001;
        S=2'b10;
        clr=0;
        #10;

        PL=4'b1001;
        S=2'b11;
        clr=0;
        #10;

        PL=4'b1001;
        S=2'b00;
        clr=0;
        #10;

        PL=4'b1001;
        S=2'b00;
        clr=1;
        #10;
    end

    initial
    begin
        $display("Test Completed!!");
        #60 $finish;
    end
endmodule

Lab_8/q4/shifter_tb.vcd
$date
	Mon Dec 12 22:09:42 2022
$end
$version
	Icarus Verilog
$end
$timescale
	1ns
$end
$scope module shiftReg4bit_tb $end
$var wire 4 ! Q [3:0] $end
$var reg 4 " PL [3:0] $end
$var reg 2 # S [1:0] $end
$var reg 1 $ clk $end
$var reg 1 % clr $end
$scope module SR $end
$var wire 4 & PL [3:0] $end
$var wire 2 ' S [1:0] $end
$var wire 1 $ clk $end
$var wire 1 % clr $end
$var reg 4 ( Q [3:0] $end
$upscope $end
$upscope $end
$enddefinitions $end
$comment Show the parameter values. $end
$dumpall
$end
#0
$dumpvars
bx (
b1 '
b1001 &
0%
0$
b1 #
b1001 "
bx !
$end
#5
b1100 !
b1100 (
1$
#10
0$
b10 #
b10 '
#15
b11 !
b11 (
1$
#20
0$
b11 #
b11 '
#25
b1001 !
b1001 (
1$
#30
0$
b0 #
b0 '
#35
1$
#40
0$
1%
#45
b0 !
b0 (
1$
